tensor_type/__init__.py
tensor_type/tensor_type.py
tensor_type-0.1.0.dist-info/LICENCE.txt
tensor_type-0.1.0.dist-info/METADATA
tensor_type-0.1.0.dist-info/WHEEL
tensor_type-0.1.0.dist-info/top_level.txt
tensor_type-0.1.0.dist-info/RECORD
