Metadata-Version: 2.1
Name: tensor-type
Version: 0.1.0
Summary: Annotates shapes of PyTorch Tensors using type annotation in Python3, and provides optional runtime shape validation.
Home-page: https://github.com/sam1902/tensor_type
Author: Samuel Prevost
Author-email: samuel.prevost@pm.me
License: BSD
Platform: UNKNOWN
Classifier: License :: OSI Approved :: BSD License
Classifier: Programming Language :: Python :: 3
Classifier: Programming Language :: Python :: 3.8
License-File: LICENCE.txt
Requires-Dist: torch
